{
  "color": {
    "narmi": {
      "moss100": { "value": "#002921" },
      "moss200": { "value": "#0F3C32" },
      "moss300": { "value": "#005242" },
      "moss400": { "value": "#006553" },
      "moss500": { "value": "#3E8373" },
      "moss600": { "value": "#6EA193" },
      "moss700": { "value": "#9DC0B6" },
      "moss800": { "value": "#CDDED9" },
      "moss": { "value": "{color.narmi.moss400.value}" },

      "pine100": { "value": "#041A14" },
      "pine200": { "value": "#062821" },
      "pine300": { "value": "#16362C" },
      "pine400": { "value": "#1A4338" },
      "pine500": { "value": "#44655B" },
      "pine600": { "value": "#708981" },
      "pine700": { "value": "#708981" },
      "pine800": { "value": "#CDD6D3" },
      "pine": { "value": "{color.narmi.pine400.value}" },

      "cove100": { "value": "#002547" },
      "cove200": { "value": "#00376A" },
      "cove300": { "value": "#094895" },
      "cove400": { "value": "#005CB2" },
      "cove500": { "value": "#237CC3" },
      "cove600": { "value": "#66A2D6" },
      "cove700": { "value": "#A6CFF0" },
      "cove800": { "value": "#D4EDFF" },
      "cove": { "value": "{color.narmi.cove400.value}" },

      "azul100": { "value": "#001340" },
      "azul200": { "value": "#00205E" },
      "azul300": { "value": "#002C82" },
      "azul400": { "value": "#003EA0" },
      "azul500": { "value": "#3664B5" },
      "azul600": { "value": "#6B89C7" },
      "azul700": { "value": "#9CB1DE" },
      "azul800": { "value": "#C9D8F2" },
      "azul": { "value": "{color.narmi.azul400.value}" },

      "pistachio100": { "value": "#485E3D" },
      "pistachio200": { "value": "#6B8C5A" },
      "pistachio300": { "value": "#90BB78" },
      "pistachio400": { "value": "#B5E995" },
      "pistachio500": { "value": "#CCF0B4" },
      "pistachio600": { "value": "#DAF4C8" },
      "pistachio700": { "value": "#E9F8DE" },
      "pistachio800": { "value": "#F7FCF3" },
      "pistachio": { "value": "{color.narmi.pistachio400.value}" },

      "cactus100": { "value": "#324C23" },
      "cactus200": { "value": "#4B7137" },
      "cactus300": { "value": "#63964B" },
      "cactus400": { "value": "#7FBC5B" },
      "cactus500": { "value": "#99CA7A" },
      "cactus600": { "value": "#B3D79A" },
      "cactus700": { "value": "#CCE4BA" },
      "cactus800": { "value": "#E5F1DC" },
      "cactus": { "value": "{color.narmi.cactus400.value}" },

      "sand100": { "value": "#423329" },
      "sand200": { "value": "#684D41" },
      "sand300": { "value": "#947564" },
      "sand400": { "value": "#C4A08A" },
      "sand500": { "value": "#DCC1A2" },
      "sand600": { "value": "#EED6C3" },
      "sand700": { "value": "#F4E3D6" },
      "sand800": { "value": "#FCF0E9" },
      "sand": { "value": "{color.narmi.sand500.value}" },

      "black": { "value": "#333333" },
      "grey": { "value": "#4C4C4C" },
      "mediumGrey": { "value": "#8C8C8C" },
      "lightGrey": { "value": "#D9D9D9" },
      "smokeGrey": { "value": "#F3F3F3" },
      "white": { "value": "#FFFFFF" }
    }
  }
}
